<?xml version="1.0"?>
<!DOCTYPE hibernate-mapping PUBLIC "-//Hibernate/Hibernate Mapping DTD 3.0//EN"
"http://hibernate.sourceforge.net/hibernate-mapping-3.0.dtd">
<!-- Generated 31-may-2013 22:17:09 by Hibernate Tools 3.2.1.GA -->
<hibernate-mapping>
    <class name="emch.modelo.entidades.TPerfil" table="t_perfil" catalog="bd_emch">
        <id name="cdPerfil" type="string">
            <column name="cdPerfil" length="4" />
            <generator class="assigned" />
        </id>
        <property name="nombrePrf" type="string">
            <column name="nombrePrf" length="30" not-null="true" />
        </property>
        <property name="descripPrf" type="string">
            <column name="descripPrf" length="200" />
        </property>
        <property name="estado" type="boolean">
            <column name="estado" not-null="true" />
        </property>
        <set name="TAccesoes" inverse="true">
            <key>
                <column name="cdPerfil" length="4" not-null="true" />
            </key>
            <one-to-many class="emch.modelo.entidades.TAccesoe" />
        </set>
        <set name="TUsuarios" inverse="true">
            <key>
                <column name="cdPerfil" length="4" not-null="true" />
            </key>
            <one-to-many class="emch.modelo.entidades.TUsuario" />
        </set>
    </class>
</hibernate-mapping>
